dynai/Handler.py
dynai/__init__.py
dynai/core.py
dynai-0.1.1.dist-info/METADATA
dynai-0.1.1.dist-info/WHEEL
dynai-0.1.1.dist-info/top_level.txt
dynai-0.1.1.dist-info/RECORD
