Metadata-Version: 2.1
Name: dynai
Version: 0.1.1
Summary: Dynamic AI
Home-page: https://dynai.readthedocs.io/
Author: Arian Ott
Author-email: learning.ott@gmail.com
License: MIT License
Classifier: Intended Audience :: Developers
Classifier: License :: OSI Approved :: MIT License
Classifier: Programming Language :: Python
Classifier: Programming Language :: Python :: 3
Classifier: Programming Language :: Python :: 3.6
Classifier: Programming Language :: Python :: 3.7
Classifier: Programming Language :: Python :: 3.8
Classifier: Programming Language :: Python :: 3.9
Classifier: Operating System :: OS Independent
Requires-Dist: requests (>=2)
Requires-Dist: beautifulsoup4
Requires-Dist: bs4
Requires-Dist: validators
